passwords_generator/__init__.py
passwords_generator/generator.py
f_passwords_generator-2.1.0.dist-info/LICENSE
f_passwords_generator-2.1.0.dist-info/METADATA
f_passwords_generator-2.1.0.dist-info/WHEEL
f_passwords_generator-2.1.0.dist-info/top_level.txt
f_passwords_generator-2.1.0.dist-info/RECORD
