Metadata-Version: 2.1
Name: f-passwords-generator
Version: 2.1.0
Summary: Strong Passwords Generator made with python.
Home-page: https://github.com/fathiabdelmalek/f-passwords-generator.git
Author: Fathi AbdelMalek
Author-email: abdelmalek.fathi.2001@gmail.com
License: OSI Approved :: MIT License
Classifier: Programming Language :: Python :: 3
Classifier: Programming Language :: Python :: 3.6
Classifier: License :: OSI Approved :: MIT License
Classifier: Operating System :: OS Independent
Requires-Python: >=3.6
License-File: LICENSE
Requires-Dist: cipherspy
